KnnClassificationRobGin/__init__.py
KnnClassificationRobGin-1.0.0.dist-info/LICENSE
KnnClassificationRobGin-1.0.0.dist-info/METADATA
KnnClassificationRobGin-1.0.0.dist-info/WHEEL
KnnClassificationRobGin-1.0.0.dist-info/top_level.txt
KnnClassificationRobGin-1.0.0.dist-info/RECORD
