Metadata-Version: 2.1
Name: KnnClassificationRobGin
Version: 1.0.0
Summary: A package for KNN Classification
Home-page: https://github.com/Mrrobi/python/tree/master/packages/KnnClassification
Author: Md Robiuddin
Author-email: mrrobi040@hotmail.com
License: UNKNOWN
Platform: UNKNOWN
Classifier: Programming Language :: Python :: 3
Classifier: License :: OSI Approved :: MIT License
Classifier: Operating System :: OS Independent
Requires-Python: >=3.6
